{
 "scenes": [
  "default",
  "8_9_10m18",
  "lea",
  "machine",
  "lea2",
  "lmd",
  "poolx",
  "thorwview",
  "blp1",
  "blp2",
  "plock"
 ],
 "active_s": "plock",
 "patterns": [
  {
   "scene": "default",
   "name": "def",
   "params": "y,x",
   "text": "`y` $ n (run 5) #s \"gen0\" #end \"0.`x`\""
  },
  {
   "scene": "default",
   "name": "s",
   "params": "",
   "text": "silence"
  },
  {
   "scene": "asd",
   "name": "pek",
   "params": "y",
   "text": "sound \"gen0 ~ ~\" # end 0.`y`"
  },
  {
   "scene": "3m18",
   "name": "s",
   "params": "",
   "text": "silence"
  },
  {
   "scene": "3m18",
   "name": "pat",
   "params": "x",
   "text": "nToOrbit $ n \"{0 ~ 1 [<~ 0 ~ 0>  ~] <0 ~ 0 > 1 <~ ~ ~ 1>}%5\" #s \"gen`x`\" #comp 0.5 "
  },
  {
   "scene": "3m18",
   "name": "hats",
   "params": "",
   "text": "( 0.2 ~>) $ nToOrbit $ n \"{0 ~ 1 [<~ 0 ~ 0>  ~] <0 ~ 0 > 1 <~ ~ ~ 1>}%5\" #s \"gen2\" #comp 0.5 |+|n \"2\" "
  },
  {
   "scene": "3m18",
   "name": "foilbass",
   "params": "",
   "text": "jux rev $ slow 2 $ n (foldl (append) \"0 3\" [\"0 3\", \"0 4\", \"0 5\", \"0 [3 6]\"]) # sound \"foil3\" # speed 2 # crush 3 # room 0.2 # size 0.1 #orbit 4"
  },
  {
   "scene": "8_9_10m18",
   "name": "s",
   "params": "",
   "text": "silence"
  },
  {
   "scene": "8_9_10m18",
   "name": "pto",
   "params": "y,z",
   "text": "nToOrbit $ `y` $ n \"{<0 <~ [~ 0] <2*3? ~> > > < ~ [0 2]> 1 < [~ 1] <2 1 1 >>, <~ 3> <~ 3> 2 <~ <3 ~ 3*2>>}%5\" #s \"gen`z`\" #comp 0.5 #rect 0.5"
  },
  {
   "scene": "8_9_10m18",
   "name": "pat",
   "params": "y",
   "text": "nToOrbit $ n  \"{<0 <~ [~ 0] <2*3? ~> > > < ~ [0 2]> 1 < [~ 1] 2> ,3 3 2 <~ 3>}%5\" #s \"`y`\" #comp 0.5 #shape 0.6 #fmf 140 #fm 0.25  #coarse 3 #lpf (scalex 3300 4300 $ sine) #lpq 0.24"
  },
  {
   "scene": "8_9_10m18",
   "name": "acd",
   "params": "",
   "text": "slow \"4\" $ n (scaleP \"minor\" $ c2p' \"{c2 ~ ~ c3 ~ f2 f3 ~ ds2 ~ ds2 ~ d2 ~ g2 as2}%5\" ((scale (0) (-3) $ sine ) * (scale (-2) (-2) $ sine * 2))) # s \"kobass\" #sustain 5 #gain 1 #orbit 4"
  },
  {
   "scene": "8_9_10m18",
   "name": "nor",
   "params": "x",
   "text": "every 8 (rev)$ n (scaleP \"minor\" $ c2p' \"{`x`}%5\" ((scale (-3) (-2) $ sine ) * (scale (-4) (1) $ tri))) # s \"acid\" #legato 1 #orbit 5"
  },
  {
   "scene": "8_9_10m18",
   "name": "hat",
   "params": "",
   "text": "spaceOut[1] $n \"{4*2 < [4 3]>}%4\"  #s \"gen5\" #orbit 3 #gain 1.2 #end 0.5 #delay 0.3"
  },
  {
   "scene": "8_9_10m18",
   "name": "fil",
   "params": "",
   "text": "sometimes (trunc 0.5) $ slow 2 $ n \"{~ <0 1 2 3> ~ <~ 4> ~}%5\" #s \"foil3\" #orbit 6 #gain 1.2 #vowel \"a u p\"  #room 0.2 #attack 0.02 #"
  },
  {
   "scene": "lea",
   "name": "sn",
   "params": "x,y",
   "text": "n \"{`x`}%5\" #s \"`y`\" #orbit 1 #end 0.`t` #speed 0.`t`"
  },
  {
   "scene": "lea",
   "name": "hh",
   "params": "x,y",
   "text": "slow 1 $ n \"{`x`}%5\" #s \"`y`\" #orbit 2 #end 0.`t`  "
  },
  {
   "scene": "lea",
   "name": "nord",
   "params": "x,z,y",
   "text": "nToOrbit $slow `x` $ n (scaleP \"minor\" $ c2p' \"{`z`}\" ((scale (-3) (2) $ `y` ) + (scale (-3) (-1) $ `y` ))) # s \"nord1\" #legato 5 "
  },
  {
   "scene": "lea",
   "name": "s",
   "params": "",
   "text": "silence"
  },
  {
   "scene": "machine",
   "name": "s",
   "params": "",
   "text": "silence"
  },
  {
   "scene": "machine",
   "name": "md",
   "params": "",
   "text": "outside 3 (someCyclesBy 0.1 $ const silence)$ nToOrbit $ sometimes (within (0.8,0.9)(off 0.5 (rev)))$slow 1.5 $ n \"{0 1 ~ 0 <~ 1> 1}%5\" #s \"blp1\" #gain 1.2 #nudge \"-0.10\""
  },
  {
   "scene": "machine",
   "name": "pat",
   "params": "y,x",
   "text": "nToOrbit $ `y` $ sometimes (within (0.&`x`-1&,0.`x`)(off 0.5 (rev)))$slow 1.5 $ n \"{0 1 ~ 0 <~ 1> 1}%5\" #s \"gen6\" #speed 0.9`t`"
  },
  {
   "scene": "machine",
   "name": "nord",
   "params": "",
   "text": "trunc 0.`t` $ slow 3 $ n (scaleP \"minor\"\"{~ ~ [c3 c4]  ~ [c2 c4 f4] ~}%5\") #s \"kobass\" #dur 4 #gain 1.1#orbit 5"
  },
  {
   "scene": "machine",
   "name": "amb",
   "params": "",
   "text": "slow 2 $ n \"0 ~ ~ ~ \" #s \"flut2\" #pan (discretise (1/2) $ scale 0.2 0.7 $ sine) #hpf (slow 1.74 $ scalex 500 2000 $ sine) #speed 1 #room 0.2 #size 0.8"
  },
  {
   "scene": "machine",
   "name": "md2",
   "params": "x",
   "text": "nToOrbit $ `x` $slow 3 $ n \"{~ [2 <3 4>] ~ ~ [4 3], 4 4*2 <4 ~>}%5\" #s (stack[ \"gen0\"]) #gain 1.1 #nudge \"-0.10\""
  },
  {
   "scene": "machine",
   "name": "apt",
   "params": "x",
   "text": "slow 1.5 $ n \"{ ~ ~ ~ ~ 2 <~ ~ ~ <2 `x`>>}%5\" #s \"bass4\" # gain (scale 0.69 1 $ slow 1.3 rand) # gain \"0.95\" # pan (scale 0.3 0.7 $ slow 1.4 rand) #orbit 5"
  },
  {
   "scene": "lea",
   "name": "kc",
   "params": "x",
   "text": "nToOrbit $ `x`$ every 10 (rev)  $ slow 1 $n \"{0 ~ 1 <~ 0> 0 <1 ~> <1 [1  1] 1 1 >}%5\" #rect 0.5  #s \"gen7\" #gain 1 #room 0.12  #speed 0.7 #lpf 8000"
  },
  {
   "scene": "lea",
   "name": "h2",
   "params": "x",
   "text": "every `x` (#cut 1)$ every 4 (#end 0.2) $ slow 1 $n \"{<4 [4 3] 4 4 >,~ ~ 4 4 <4 3>, <3 3?> }%5\"  #s \"gen`x`\" #orbit 4 #gain 1 #end 1 #pan (discretise 2 $ scale 0.43 0.65 $ sine)"
  },
  {
   "scene": "machine",
   "name": "apt2",
   "params": "y,x",
   "text": "`y` $ slow 1.5 $ n \"{ ~ <~ `x`> ~ ~ 2 <~ ~ ~ <2 `x`>>}%5\" #s \"bass`x`\" # gain (scale 0.69 1 $ slow 1.3 rand) # gain \"0.95\" # pan (scale 0.3 0.7 $ slow 1.4 rand) #orbit 5"
  },
  {
   "scene": "machine",
   "name": "h2",
   "params": "x",
   "text": "every `x` (#cut 1)$ every 4 (#end 0.2) $ slow 1.5 $n \"{<4 [4 3] 4 4 >,~ ~ 4 4 <4 3>, <3 3?> }%5\"  #s \"gen`x`\" #orbit 4 #gain 1 #end (scale 0.01 2 $ sine) #pan (discretise 2 $ scale 0.43 0.65 $ sine) "
  },
  {
   "scene": "lea",
   "name": "kc2",
   "params": "x,y",
   "text": "nToOrbit $ `x`$ every 10 (rev)  $ slow 1 $n \"{0 ~ 1 <~ 0> 0 <1 ~> <1 [1  1] 1 1 >}%5\" #rect 0.5  #s \"gen`y`\" #gain 1 #room 0.12  #speed 0.7 #lpf 8000"
  },
  {
   "scene": "lea2",
   "name": "sn",
   "params": "x,y",
   "text": "n \"{`x`}%5\" #s \"`y`\" #orbit 1 #end 0.`t` #speed 0.`t`"
  },
  {
   "scene": "lea2",
   "name": "hh",
   "params": "x,y",
   "text": "inside 3 (#cut 1)$slow 1 $ n \"{`x`}%5\" #s \"`y`\" #orbit 2 #end 0.`t`  "
  },
  {
   "scene": "lea2",
   "name": "nord",
   "params": "x,z,y",
   "text": "nToOrbit $slow `x` $ n (scaleP \"minor\" $ c2p' \"{`z`}\" ((scale (-3) (2) $ `y` ) + (scale (-3) (-1) $ `y` ))) # s \"iac1\" #legato 5 "
  },
  {
   "scene": "lea2",
   "name": "s",
   "params": "",
   "text": "silence"
  },
  {
   "scene": "lea2",
   "name": "kc",
   "params": "x",
   "text": "modNote 3 (#end (disc 16 $ scale 0.01 0.2 $ saw))$ nToOrbit $ `x`$ every 10 (rev)  $ slow 1 $n \"{0 ~ 1 <~ 0> 0 <1 ~> <1 [1  1] 1 1 >}%5\" #rect 0.5  #s \"gen1\" #gain 1 #comp 0.5"
  },
  {
   "scene": "lea2",
   "name": "h2",
   "params": "x",
   "text": "every `x` (#cut 1)$ every 4 (#end 0.2) $ slow 1 $n \"{<4 [4 3] 4 4 >,~ ~ 4 4 <4 3>, <3 3?> }%5\"  #s \"gen`x`\" #orbit 4 #gain 1 #end 1 #pan (discretise 2 $ scale 0.43 0.65 $ sine)"
  },
  {
   "scene": "lea2",
   "name": "kc2",
   "params": "x,y",
   "text": "nToOrbit $ modNote 2 (#lpf (slow 4 $ disc 16 $ scale 5000 12000 $ saw)) $ modNote 1 (#speed (disc 16 $ scale 0.69 1.1 $ saw))$ modNote 3 (#end (disc 16 $ scale 0.01 0.2 $ saw))$ `x`$ every 10 (rev)  $ slow 1 $n \"{0 ~ 1 <~ 0> 0 <1 ~> <1 [1  1] 1 1 >}%5\" #rect 0.5  #s \"gen`y`\" #gain 1 #room 0.12 "
  },
  {
   "scene": "lea2",
   "name": "apt",
   "params": "x",
   "text": "n \"{ ~ ~ ~ ~ 2 <~ ~ ~ <2 `x`>>}%5\" #s \"bass4\" # gain (scale 0.69 1 $ slow 1.3 rand) # gain \"1.2\" # pan (scale 0.3 0.7 $ slow 1.4 rand) #orbit 5"
  },
  {
   "scene": "lea2",
   "name": "nba",
   "params": "z,y,x",
   "text": "every 10 (rev) $ slow 2 $ up (scaleP \"minor\" $ c2p' \"{`z`}%5\" ((scale (-2) (2) $ `y` *2 ) * (scale (-2) (2) $ `y` *4 ))) #sound \"bass`x`\" #orbit 5 "
  },
  {
   "scene": "lea2",
   "name": "h22",
   "params": "x",
   "text": "every `x` (#cut 1)$ every 4 (#end 0.2) $ slow 4 $n \"{<4 [4 3] 4 4 >,~ ~ 4 4 <4 3>, <3 3?> }%5\"  #s \"gen`x`\" #orbit 4 #gain 1 #end 1 #pan (discretise 2 $ scale 0.43 0.65 $ sine)"
  },
  {
   "scene": "lmd",
   "name": "sn",
   "params": "x",
   "text": "n \"{`x`}%5\" #stack [|*|ctlNum \"40\" #control (slow 4 $ scale 0 127 $ sine)] #s \"md1\" #midicmd \"[noteOn, control]\""
  },
  {
   "scene": "lmd",
   "name": "hh",
   "params": "x,y",
   "text": "slow 1 $ n \"{`x`}%5\" #s \"`y`\" #orbit 2 #end 0.`t`  "
  },
  {
   "scene": "lmd",
   "name": "nord",
   "params": "x,y",
   "text": "slow `x` $ n (`y` \"minor\" \"{<g4 bs4> es5 ~ [b4 <b5 g5 g4 bs4>]}%5 \") #s \"iac\" #legato (slow 16 $ spaceOut[0.2..3.2]) "
  },
  {
   "scene": "lmd",
   "name": "s",
   "params": "",
   "text": "silence"
  },
  {
   "scene": "lmd",
   "name": "kc",
   "params": "x",
   "text": "mfold$`x`$n \"14\" #s \"md1*5\" #gain 1.2 #ccn (stack [50,46,47]) #ccv (slow 4 $ scale 10 127 $ sine) #midicmd \"[noteOn, control]\""
  },
  {
   "scene": "lmd",
   "name": "h2",
   "params": "x",
   "text": "every `x` (#cut 1)$ every 4 (#end 0.2) $ slow 1 $n \"{<4 [4 3] 4 4 >,~ ~ 4 4 <4 3>, <3 3?> }%5\"  #s \"gen`x`\" #orbit 4 #gain 1 #end 1 #pan (discretise 2 $ scale 0.43 0.65 $ sine)"
  },
  {
   "scene": "lmd",
   "name": "kc2",
   "params": "x,y",
   "text": "nToOrbit $ `x`$ every 10 (rev)  $ slow 1 $n \"{0 ~ 1 <~ 0> 0 <1 ~> <1 [1  1] 1 1 >}%5\" #comp 0.5  #s \"gen`y`\" #gain 1 #lpq 0.22 #lpf 8900"
  },
  {
   "scene": "lmd",
   "name": "apt",
   "params": "",
   "text": "within (0.6,0.9) (hurry 3) $ inside 2(every 5 (#room 0.2))$ slow 5$ note (harmonise \"minor\" $ c2p' (\"{gs3 gs3 g3 ~ [~ c4] [~ ds4]}\") ((scale (-3) (-2) $ sine ) * (scale (2) (5) $ sine ))) #s \"kobass\" #sustain 2 #size 0.28 #lpf 5000 |+|n \"-12\" #lpq 0.2 #orbit 5"
  },
  {
   "scene": "lmd",
   "name": "nba",
   "params": "",
   "text": "within (0.1,0.5) (off 0.5 (hurry 3)) $ inside 2(every 5 (#room 0.24))$ slow 5$ note (scaleP \"minor\" $ c2p' (\"{gs3 gs3 g3 e4 [~ c4] [~ ds4]}\") ((scale (-3) (-2) $ sine ) * (scale (2) (5) $ sine ))) #s \"kobass\" #sustain 2 #size 0.8 #lpf 5000 |+|n \"-12\" #lpq 0.2 #orbit 5\n"
  },
  {
   "scene": "lmd",
   "name": "h22",
   "params": "x",
   "text": "slow 5  $ within (0.`x`,0.&`x`+3&) (hurry 3) $ n (scaleP \"minor\" $ c2p' (\"{gs3 [gs3 g3] [c4 ds4]}%5\") ((scale (0.1) (0.6) $ sine *2) * (scale (-2.0) (3.5) $ sine*4 ))) #s \"acid\" #sustain 0.5 |+|n \"0\" #lpq 0.2 #orbit 4 #lpf 4000 "
  },
  {
   "scene": "lmd",
   "name": "rav",
   "params": "",
   "text": "every 10 (rev)  $ slow 1 $n \"{0 ~ 1 <~ 0> 0 <1 ~> <1 [1  1] 1 1 >}%5\" #s \"md1\" #gain 1.2 #ccn \"73\" #ccv (scale 55 127 tri) #mcmd"
  },
  {
   "scene": "lmd",
   "name": "sq",
   "params": "",
   "text": "slow 2 $nToOrbit $  n \"{0 < ~ ~ 0 ~> 1 0  [~ 1] <~ 0 0 0 0 1 0 ~ > <  [ <0 ~> 1] [ 1 <~ 1 0 1 ~>]> }%5\" #s \"808\" #comp 0.5 #end 0.2"
  },
  {
   "scene": "lmd",
   "name": "sq2",
   "params": "y,x",
   "text": "slow 2 $ nToOrbit $ `y` $  toggles \"`x`\" [n \"{0 < ~ ~ 0 ~> 1 0  [~ 1] <~ 1 ~ > <  [ <3 ~> [~ 1]] [ 1 <~ 1 3 1 ~>] > }%5\" #s \"gen3\" #speed 1 ,n \"{<3 5 2 6 >, <3 3 3*2 3> , 3}%5\"#s \"gen3\" #speed 1 , n \"{0 < ~ ~ 0 ~> 1 0  [~ 1] <~ 0 0 0 0 1 0 ~ > <  [ <0 ~> [~ 1]] [ 1 <~ 1 0 1 ~>]> }%5\" #s \"gen1\" #speed 0.5 , (0.125 <~) $  n \"{3 < ~ ~ ~ ~> 1 3  [~ 1] <~ 3 ~ > <  [ <3 ~> [~ 1]] [ 1 <~ 1 3 1 ~>] > }%5\" #s \"gen4\" #speed 1 ,n \"{3 < ~ ~ ~ ~> 1 3  [~ 1] <~ 3 ~ > <  [ <3 ~> [~ 1]] [ 1 <~ 1 3 1 ~>] > }%5\" #s \"foil1\" #speed 0.5 ] "
  },
  {
   "scene": "poolx",
   "name": "s",
   "params": "",
   "text": "silence"
  },
  {
   "scene": "poolx",
   "name": "foil",
   "params": "x",
   "text": "rarely(|+|n 1) $ slow 2 $ n \"1\" #s \"foil0\" #orbit 4 #pan (scale 0.3 0.66 $ saw) #room 0.1 #size 0.4 #`x` "
  },
  {
   "scene": "poolx",
   "name": "foil2",
   "params": "",
   "text": "sometimes (striate 8 ) $ slow 4 $ n \"1\" #s \"foil0\" #orbit 4 #hpf 1000 #release 8 #attack 0.1 #delay 0.3 #delayfb 0.69 "
  },
  {
   "scene": "poolx",
   "name": "foil3",
   "params": "",
   "text": "slow 2 $ rarely (modNote 1 (#speed \"-1\"))$ modNote 1 (# coarse \"<12 1.5 2 3 4>\") $ n \"{0 1 ~ 0 0 1}%3\" #s \"foil2\" #orbit 4\n"
  },
  {
   "scene": "poolx",
   "name": "pat",
   "params": "",
   "text": "nToOrbit $ sometimes (modNote 0 (#s \"<gen8 gen7 gen7>\"))$ slow 1.5 $ rarely (modNote 1 (#room \"0.52\"))$modNote 3 ((#coarse \"<0 0 0 24 12>\").(#vowel \"a e>\") .(# end \"<0.5 1.5 0.7>\")) $ n \"{0 ~ 1 0 0 <1 [1 ~]> [~ 1] <0 [2 3 4]>,[4 3] 3 }%5\" #s \"gen5\" "
  },
  {
   "scene": "poolx",
   "name": "patslow",
   "params": "",
   "text": "slow 2 $ nToOrbit$ modNote 0 ((#speed \"<0.25 0.5 0.25>\").(#lpf \"<7000 6500 2400>\").(#lpq \"<0.22 0.3>\"))$ modNote 1(#speed \"<0.55 0.45 0.51 0.51>\")$modNote 1 (#gain (scale 1.1 1.3 $ saw ))$ rarely (modNote 1 (#room \"<0.3 0.52>\")) $ n\"0 [1 ~]  < ~ 0 [< ~ 1?> ~ ]> <~ 0> [ ~1] <~ ~ <[2 3] 1?>>\"#s \"gen0\" #comp 0.5 #freeze 0.0 "
  },
  {
   "scene": "poolx",
   "name": "kobass",
   "params": "",
   "text": "rarely (hurry 3) $ degradeBy 0.3 $ within (0.6,0.89) (hurry 3) $ inside 2(every 5 (#room 0.2))$ slow 12$ note (scaleP \"major\" $ c2p' (\"{gs4 <eb4 gs4> g4 ~ [~ c4] [~ <ds4 ds5>]}\") ((scale (-1) (-2) $ sine ) * (scale (2) (1) $ sine ))) #s \"kobass\" #sustain 2 #orbit 5  |+|n \"<-24 -32 -12>\""
  },
  {
   "scene": "poolx",
   "name": "kob2",
   "params": "",
   "text": "slow 12$ note (scaleP \"major\" $ c2p' (n \"0 [1 ~]  < ~ ~ [1 1]> <~ 0> <0 ~> [ ~1] <~ ~ ~ <[2 3] 1>>\" ) ((scale (-1) (-2) $ sine ) * (scale (2) (1) $ sine ))) #s \"kobass\" #sustain 2 #orbit 5  |+|n \"<-24 -18 -12>\""
  },
  {
   "scene": "poolx",
   "name": "md2",
   "params": "",
   "text": "slow 2 $ modNote 3 (#gain (scale 1.1 1.3 $ saw ))$ rarely (modNote 1 (#ccn \"<73 76>\")) $ n \"0 [1 ~]  < ~ 0 [< ~ 1?> ~ ]> <~ 0> [ ~1] <~ ~ <[2 3] 1?>>\" #s \"md\" #nudge \"-0.10\""
  },
  {
   "scene": "poolx",
   "name": "mdh",
   "params": "",
   "text": "slow 2 $ modNote 3 (#gain (scale 1.1 1.3 $ saw ))$ rarely (modNote 1 (#ccn \"<73 76>\")) $ n \"{4 <2 2> <[< ~ 2*2? 2> 2] [ 7 5 6] 2>, 7}\" #s \"md\" #nudge \"-0.10\" #ccn \"{40, 47, 46?}\" #ccv (scale 0 127 $ (saw * tri)) #midichan 1 #mcmd "
  },
  {
   "scene": "poolx",
   "name": "md3",
   "params": "",
   "text": "slow 2 $n \"{11, [ 3 12]}\" #s \"md\" #nudge \"-0.10\" # ccn \"{85, 78}\" #ccv (slow 2 $ scale 64 127 $ saw) #midichan 2 #mcmd "
  },
  {
   "scene": "thorwview",
   "name": "s",
   "params": "",
   "text": "silence"
  },
  {
   "scene": "thorwview",
   "name": "pto",
   "params": "y",
   "text": "every 12 (rev) $ `y` $ n \"{<0 <~ [~ 0] <<1*2 2 2*3?> ~> > > < ~ [0 2]> 1 < [~ 1] <2 1 1 >>}%3\" #s \"<bass0 bass2 bass1 bass3 bass1>\" #gain 1.4  #cut 6  #orbit 5"
  },
  {
   "scene": "thorwview",
   "name": "pat",
   "params": "",
   "text": "nToOrbit $ n  \"{<0 <~ [~ 0] <<2*3?> ~> > > <0? [0 0] 0> < <1*3 2*3 0> ~ [0 2?]> 1 < [~ 1] 2> }%3\" #s \"gen2\"  #gain 1.4"
  },
  {
   "scene": "thorwview",
   "name": "acd",
   "params": "",
   "text": "slow \"16\" $ up (scaleP \"minor\" $ c2p' \"{c2 ~ ~ c3 ~ f2 f3 ~ ds2 ~ ds2 ~ d2 ~ g2 as2}%8\" ((scale (0) (-3) $ sine ) * (scale (-2) (-2) $ sine * 2))) # s \"bass2\" #gain 1 #orbit 4 #lpf (scale 8000 12000 $sine *2)"
  },
  {
   "scene": "thorwview",
   "name": "nor",
   "params": "x",
   "text": "every 8 (rev)$ n (scaleP \"minor\" $ c2p' \"{`x`}%5\" ((scale (5) (-2) $ sine ) * (scale (-1) (1) $ tri))) # s \"nord1\" #legato 1 #orbit 4 #gain 1.2"
  },
  {
   "scene": "thorwview",
   "name": "hat",
   "params": "",
   "text": "slow 2 $ n \"{4*2 < [4 3]>}%3\"  #s \"gen5\" #orbit 3 #gain 1.2 #end 0.5 #delay 0.3"
  },
  {
   "scene": "thorwview",
   "name": "fil",
   "params": "",
   "text": "sometimes (trunc 0.5) $ slow 2 $ n \"{~ <0 1 2 3> ~ <~ 4> ~}%5\" #s \"foil3\" #orbit 6 #gain 1.2 #vowel \"a u p\"  #room 0.2 #attack 0.02 #"
  },
  {
   "scene": "blp1",
   "name": "s",
   "params": "",
   "text": "silence"
  },
  {
   "scene": "blp1",
   "name": "pat",
   "params": "y,x",
   "text": "nToOrbit $ modNote 0 (#speed \"< 1 1 0.5>\")$ modNote 1 (#delay \"<0.075 0.51>\")$ modNote 2 (#speed \"<1 1>\") $ modNote 3 (#speed \"<0.5 0.75 1>\")$ n \"{0 [ <3*2 4 ~> 3 <[2 3] 4 <~ 2*2>> ] 1 ~ <~ 0 > }%6\" #s \"`y`\" #comp 0.5 #`x` (disc (2)$ choose [0.2,0.04,0.05,0.06,0.055,0.044,0.033,0.22,0.101,0.01]) #delayfb 0.276 #delay 0.0"
  },
  {
   "scene": "blp1",
   "name": "zow",
   "params": "x",
   "text": "slow 6 $ n (scaleP \"major\"\"{[g3 es2] ~ ~ }%5\") #s \"supercomparator\"  #sustain 6 #slide \"< 0.5 0.1 0.3>\" #gain 1.2 `x` #orbit 5"
  },
  {
   "scene": "blp1",
   "name": "blp",
   "params": "",
   "text": "modNote 1 (#speed \"<1 1 1 1 0.5>\")$ modNote 3 (#delay \"<0.59 0.51>\")$ modNote 2 (#speed \"<1 -1>\") $ modNote 3 (#speed \"<0.5 0.75 1>\")$ n \"{0 [ <3*2 4 ~> 3 <[2 3] 4 ~> ] 1 ~ <0 ~ [2 2 3]> }%5\" #s \"blp_weave\" #comp 0.5 #delaytime (disc (2)$ choose [0.02,0.04,0.05,0.044,0.055,0.044,0.033,0.022,0.011,0.1]) #delayfb 0.29 #delay 0.0 #nudge 0.33 #cut 1 |+|n \"0\" #speed 2"
  },
  {
   "scene": "blp1",
   "name": "blp2",
   "params": "",
   "text": "nToOrbit $ slow 2 $  modNote 1 (#speed \"<1 1 1 1 0.5>\")$ modNote 3 (#delay \"<0.01 0.59 0.51>\")$ modNote 2 (#speed \"<1 -1>\") $ modNote 3 (#speed \"<0.5 0.75 1>\")$ n \"{0 [ <3*2 4 ~> 3 <[2 3] 4 ~> ] 1 ~ <0 ~ [2 2 3]> }%6\" #s \"blp0\" #speed 0.5 |+|n 1 "
  },
  {
   "scene": "blp1",
   "name": "pat2",
   "params": "y,x",
   "text": "slow 2 $ nToOrbit $  modNote 0 (#speed \"< 1 1 0.5>\")$ modNote 1 (#delay \"<0.25 0.11>\")$ modNote 2 (#speed \"<1 1>\") $ modNote 3 (#speed \"<0.5 0.75 1>\")$ n \"{0 [ <3*2 [2 4] 0> 3 <[2 3] 4 <1 <[2 3] 2*2>>> ] <1 ~> < ~ 1> <~ 0 > }%5\" #s \"`y`\" #comp 0.6 #`x` (disc (2)$ choose [0.2,0.04,0.05,0.6,0.55,0.044,0.33,0.22,0.11,0.1]) #delayfb 0.9 #delay 0.0"
  },
  {
   "scene": "blp1",
   "name": "glt",
   "params": "",
   "text": "slow 3 $ juxBy 0.3 (|+|n \"2\") $ n (run 5) #s \"blp_nunu\" #orbit 4  #speed \"<0.5 0.8>\" #lpf (disc (1/5) $ fast 4 $ scale 4000 12000 $ saw) #lpq 0.4  #comb (disc (1/5) $ fast 4 $ scale 0.1 0.6 $ saw) #coarse\"<12 4 0>\" "
  },
  {
   "scene": "blp1",
   "name": "pat1",
   "params": "",
   "text": "nToOrbit $ modNote 2 ((#freeze 0.2). (#nudge\"0.00125\")) $ off 0.5 ((#s \"blp_nunu\").(#n (run 3)))$ slow 1 $ n \"{0 ~ 2 0 <~ 0> 2 ~}%6\" #s \"blp0\" #comb (disc (1/5) $ fast 4 $ scale 0.00110 0.00125 $ saw) #comp 0.5 #gain 1.1  #sustain (fast 4 $ scale 0.151 0.5 $ saw)"
  },
  {
   "scene": "blp1",
   "name": "glt2",
   "params": "",
   "text": "slow 4$ n \"{~ ~ [4 <3 4 2>] ~ <4 ~> 3 1}%6\" #s \"blp_nunu\" #orbit 4  #lpf (disc (1/6) $ fast 6 $ scale 4000 10000 $ saw) #lpq 0.34  #comb (disc (1/5) $ fast 4 $ scale 0.1 0.6 $ saw) #speed 0.5 #pan (fast 8$ scale 0.26 0.76 $ sine) #coarse 2  #accelerate (disc (1/6)$scale 0.1 0.5 $ saw)"
  },
  {
   "scene": "blp1",
   "name": "nord",
   "params": "",
   "text": "every 8 (off 0.2(#n (harmonise \"major\"\"[c3 c4 c5]\")))$slow \"<6 2 >\"  $ n (scaleP \"minor\"\"{c5 g5 e5 d5 ~ [<c4 c5> g4]}%6\") #s \"nord\" #chan 1  #gain 1 |-|n \"12\" #sustain 0.1"
  },
  {
   "scene": "blp2",
   "name": "s",
   "params": "",
   "text": "silence"
  },
  {
   "scene": "blp2",
   "name": "pat",
   "params": "",
   "text": "chop 2 $ slow (7/3) $ nToOrbit $ modNote 0 ((#lpf 500).(#lpq 0.1)) $modNote 1 ((#speed 0.5).(#psrate (disc (16) $scale 0.9 2 $ saw*2)))$ modNote 2 ((#end 1).(#speed 0.5))$ modNote 3 ((#comb 0.7).(#lbrick 0.2))$ modNote 4 ((#lpf 8000).(#room 0.3).(#comb (disc (16) $scale 0.9 2.9 $ saw*3)).(#detune (disc (16) $scale 0.9 9 $ tri*2)).(#gain 1.2).(#coarse \"<12 24 0 12>\").(#octer 0.91).(#sustain (disc (8) $scale 0.9 3 $ rand*2)).(#speed (disc (16) $scale 0.9 3 $ saw*2 * sine))) $ n \"{0 4  1 0 <4 0> 1 <4 1 [1 [2 3]]>, 4} \" #s \"blp1\" #comp 0.5 "
  },
  {
   "scene": "blp2",
   "name": "glt",
   "params": "",
   "text": "slow (14/3)  $ juxBy 0.3 (|+|n \"2\") $ n \"2\" #s  \"blp_nunu\"  #speed (disc (16) $scale 0.9 3 $ saw*2 * sine)  #orbit 4"
  },
  {
   "scene": "blp2",
   "name": "pat2",
   "params": "x",
   "text": "chop 2 $ slow (7/3) $ nToOrbit $ modNote 0 ((#lpf 500).(#lpq 0.1)) $modNote 1 ((#speed 0.5).(#psrate (disc (16) $scale 0.9 2 $ saw*2)))$ modNote 2 ((#end 1).(#speed 0.5))$ modNote 3 ((#comb 0.7).(#lbrick 0.2))$ modNote 4 ((#lpf 8000).(#room 0.3).(#comb (disc (16) $scale 0.9 2.9 $ saw*3)).(#detune (disc (16) $scale 0.9 9 $ tri*2)).(#gain 1.2).(#coarse \"<12 12 0 12>\").(#octer 0.91).(#sustain (disc (8) $scale 0.9 3 $ rand*2)).(#speed (disc (16) $scale 0.9 3 $ saw*2 * sine))) $ n \"{3 4  1 3 <4 3> 1 <4 1 [1 [2 3]]>, 4} \" #s \"`x`\" #comp 0.5 "
  },
  {
   "scene": "blp2",
   "name": "snr",
   "params": "y,x",
   "text": "slow (7/3) $ n \"{~ 2 ~ <[~ ~ ~[2 2 2?]] [~ 2]>  ~}\" #s\"`y`\" #speed 1 #orbit 2 #lbrick 0.5 `x` #comp 0.5"
  },
  {
   "scene": "plock",
   "name": "p1",
   "params": "y,x,z",
   "text": "slow 2  $nToOrbit $modNote 3 (#pan (rand)) $ modNote 3 (#end (slow 3 $ disc `y` $ scale 0.09 1 $ sine )) $ modNote 2 (#room \"<0.0 0.24>\" ) $ modNote 2(#end \"<1 1 0.75 1 1 1 0.85>\") $ modValuesF `x`_p (< 0.5) (chop 4)$ modValuesF n_p (> 1 ) (echo 12)$modValuesF lpf_p ( < 5000) ((#s \"blp_nunu*4?\").(#lpf 3000).(#speed 0.3))$n \"{0 2 [~ 0] ~ 2 <~ 2 0 [ ~ 2] >, 3*2 4?}\" #s \"`z`\" # lpf (disc `y` $ scale 2000 10000 $ saw) # lpq 0.2 #comp 0.5 #`x` (slow 2 $disc `y` $ scale 0.09 0.69 $ saw)"
  },
  {
   "scene": "plock",
   "name": "p2",
   "params": "r,y,x,z",
   "text": "every 8 (cap 0.2 0.3 )$ every 12 (foldp )  $ slow 2 $ off 0.5 (#s \"`r`\")$ someCyclesBy 0.1 (trunc 0.9)$slow 1  $nToOrbit $modNote 3 ((#pan (scale 0.3 0.6 $ saw)).(#speed \"<0.5 0.51 0.52 0.50 0.52 0.55>\" ).(#coarse 4).(#end \"<0.2 0.5 1>\")) $ modNote 1 (#end (slow 3 $ disc `y` $ scale 0.9 1 $ sine )) $ modNote 2 (#room \"<0.0 0.24>\" ) $ modNote 3(#end \"<0.251 0.1 0.285>\") $ modValuesF `x`_p (< 0.5) (chop 4)$modValuesF lpf_p ( < 7500) ((#s \"`r`*4?\").(#lpf \"<5000 3000>\").(#speed \"-0.5\"))$n \"{0 1 [~ 0] <~ 0> 1 <1 <~ 1 0 [ ~ 1]>>, 3 ~ 3 ~  [3 3 ]}%5\" #s \"`z`\" # lpf (disc `y` $ scale 6009 10000 $ saw) # lpq 0.2 #comp 0.5 #`x` (slow 2 $disc `y` $ scale 0.09 0.69 $ saw) #cut \"-1\" #fmf 300"
  },
  {
   "scene": "plock",
   "name": "s",
   "params": "",
   "text": "silence"
  },
  {
   "scene": "plock",
   "name": "amen",
   "params": "x,y",
   "text": "every 20 (rev) $ modNote `x` ((#pan (scale 0.3 0.6 $ saw)).(#speed \"<0.5 0.51 0.52 0.50 0.52 0.55>\" ).(#coarse 4).(#end \"<0.2 0.5 1>\")) $ modNote `t` (#hall \"<0.0 0.44>\" ) $ modNote `x`(#hall \"<0.251 0.1 0.285>\") $ n \"{<0 `t`> [`x` 9] [0 `t`] <`x` 0> 9 <<1 <`x` 1 0 [ `x` `t`]>> <3 &`t`+2& `x` > <[0 ~] [ ~1]> < 5 6> `x` [5 [2 1] ]>}%5\" #s \"amencutup\" # lpf (disc `x` $ scale 6009 10000 $ saw) # lpq 0.2 #comp 0.5 #`y` (slow 2 $disc `x` $ scale 0.09 0.69 $ saw) |+|n 0 #gain (disc `x` $ scale 0.98 1.1 $ rand) #orbit 3"
  },
  {
   "scene": "plock",
   "name": "amen2",
   "params": "x,y",
   "text": "every 8 (rev) $ every 4 (cap 0.2 0.`t`)$n \"{`x` 10 [~ <`x` &`x`+2&>] `t` [2 3] [10 11] }%5\" #s \"amencutup\" # lpf (disc `x` $ scale 6009 10000 $ saw) # lpq 0.2 #comp 0.5 #`y` (slow 2 $disc `x` $ scale 0.09 0.69 $ saw) |+|n 0 #orbit 3"
  },
  {
   "scene": "plock",
   "name": "amen3",
   "params": "x,y",
   "text": "every 8 (rev) $ every 4 (cap 0.2 0.`t`)$n \"{`x` 10 [~ <`x` &`x`+2&>] `t` [2 3] [10 11] }%5\" #s \"amencutup\" # lpf (disc `x` $ scale 6009 10000 $ saw) # lpq 0.2 #comp 0.5 #`y` (slow 2 $disc `x` $ scale 0.09 0.69 $ saw) |+|n 0  #orbit 3"
  },
  {
   "scene": "plock",
   "name": "gen",
   "params": "",
   "text": "every 6 ((#n \"{0 2 ~ 1 1*2 }%5\" ).(rev)) $every 2 (#n \"{~ 1 [2? 1] [2 3]}%5\" ) $n \"{0 1 ~ 0 1 }%5 \" #s \"gen1\" #speed \"1\" #shape \"0.2 0.35\" #gain \"1\" #hall 0.1"
  }
 ],
 "channels": [
  {
   "scene": "default",
   "name": "d1",
   "type": "Tidal",
   "steps": 9,
   "cells": [
    "",
    "s",
    "def `off 0.5 (#speed 2) ` `4`",
    "s",
    "def `slow 8 $ juxBy 0.5 (#s \"gen3\") ` `2`",
    "s",
    "def `juxBy 0.5 (#begin 0.2) ` `1`",
    "",
    ""
   ],
   "transition": "",
   "rate": 8,
   "gate": true,
   "solo": false,
   "mute": false,
   "loop": true,
   "selected": false,
   "time": 0,
   "cid": 0
  },
  {
   "scene": "asd",
   "name": "d2",
   "type": "Tidal",
   "steps": "4",
   "rate": 8,
   "time": 0,
   "transition": "",
   "cells": [
    "",
    "pek `5`",
    "",
    ""
   ],
   "gate": false,
   "solo": false,
   "mute": false,
   "loop": true,
   "selected": false,
   "cid": 1
  },
  {
   "scene": "default",
   "name": "d2",
   "type": "Tidal",
   "steps": 9,
   "rate": 8,
   "time": 0,
   "transition": "",
   "cells": [
    "",
    "s",
    "def `juxBy 0.5 (#coarse 12) ` `9`",
    "s",
    "def `slow 11 $ juxBy 0.5 (#s \"gen3\") ` `2`",
    "s",
    "def `off 0.5 (#room 0.2) ` `1`",
    "",
    ""
   ],
   "gate": true,
   "solo": false,
   "mute": false,
   "loop": true,
   "selected": false,
   "cid": 2
  },
  {
   "scene": "default",
   "name": "d3",
   "type": "Tidal",
   "steps": 9,
   "rate": 8,
   "time": 0,
   "transition": "",
   "cells": [
    "",
    "s",
    "def `juxBy 0.5 (#coarse  2) ` `5`",
    "s",
    "def `juxBy 0.5 (#s \"gen2\") ` `1`",
    "s",
    "def `off 0.5 (#speed 2) ` `1`",
    "",
    ""
   ],
   "gate": true,
   "solo": false,
   "mute": false,
   "loop": true,
   "selected": false,
   "cid": 3
  },
  {
   "scene": "default",
   "name": "d4",
   "type": "Tidal",
   "steps": 9,
   "rate": 8,
   "time": 0,
   "transition": "",
   "cells": [
    "",
    "s",
    "def `juxBy 0.5 (#s \"gen3\") ` `5`",
    "s",
    "",
    "s",
    "def `juxBy 0.5 (#s \"foil2\") ` `5`",
    "",
    ""
   ],
   "gate": true,
   "solo": false,
   "mute": false,
   "loop": true,
   "selected": false,
   "cid": 4
  },
  {
   "scene": "default",
   "name": "d5",
   "type": "Tidal",
   "steps": 9,
   "rate": 8,
   "time": 0,
   "transition": "",
   "cells": [
    "",
    "s",
    "def `juxBy 0.5 (#s \"water\") ` `2`",
    "s",
    "",
    "s",
    "def `juxBy 0.5 (#s \"foil2\") ` `2`",
    "",
    ""
   ],
   "gate": true,
   "solo": false,
   "mute": false,
   "loop": true,
   "selected": false,
   "cid": 5
  },
  {
   "scene": "asd",
   "name": "d",
   "type": "Tidal",
   "steps": 6,
   "rate": 8,
   "time": 0,
   "cells": [
    "",
    "",
    "",
    "",
    "",
    ""
   ],
   "gate": false,
   "solo": false,
   "mute": false,
   "loop": true,
   "executed": false,
   "selected": false,
   "cid": 6
  },
  {
   "scene": "default",
   "name": "d6",
   "type": "Tidal",
   "steps": 8,
   "rate": 8,
   "time": 0,
   "transition": "",
   "cells": [
    "",
    "",
    "",
    "",
    "",
    "",
    "",
    ""
   ],
   "gate": true,
   "solo": false,
   "mute": false,
   "loop": true,
   "executed": false,
   "selected": false,
   "cid": 7
  },
  {
   "scene": "3m18",
   "name": "d1",
   "type": "Tidal",
   "steps": 8,
   "rate": 8,
   "time": 0,
   "transition": "",
   "cells": [
    "pat `1`",
    "pat",
    "pat `1`",
    "",
    "pat `1`",
    "pat `1`",
    "",
    ""
   ],
   "gate": true,
   "solo": false,
   "mute": false,
   "loop": true,
   "executed": false,
   "selected": false,
   "cid": 12
  },
  {
   "scene": "8_9_10m18",
   "name": "d1",
   "type": "Tidal",
   "steps": 14,
   "rate": 2,
   "time": 0,
   "transition": "(clutchIn 4)",
   "cells": [
    "",
    "",
    "",
    "",
    "",
    "",
    "pto `trunc 1` `2`",
    "",
    "pto `trunc 1` `4`",
    "s",
    "pto `trunc 1` `8`",
    "pto `trunc 0.5 $ slow 1` `3`",
    "pto `juxBy 0.1(#s \"foil2\") $ slow 1` `6`",
    "pto `slow 3 $ cap 0.2 0.3`  `6`"
   ],
   "gate": true,
   "solo": true,
   "mute": false,
   "loop": true,
   "executed": false,
   "selected": false,
   "cid": 21,
   "activeSceneIndex": 0
  },
  {
   "scene": "8_9_10m18",
   "name": "d2",
   "type": "Tidal",
   "steps": 14,
   "rate": 1,
   "time": 0,
   "transition": "(clutchIn 4)",
   "cells": [
    "",
    "s",
    "pat `gen8`",
    "",
    "",
    "s",
    "pat `gen3`",
    "",
    "s",
    "pat `gen1`",
    "",
    "",
    "",
    "pat `gen8`"
   ],
   "gate": true,
   "solo": false,
   "mute": false,
   "loop": true,
   "executed": false,
   "selected": false,
   "cid": 22,
   "activeSceneIndex": 1
  },
  {
   "scene": "8_9_10m18",
   "name": "d3",
   "type": "Tidal",
   "steps": 14,
   "rate": 2,
   "time": 0,
   "transition": "(clutchIn 4)",
   "cells": [
    "",
    "s",
    "nor `x ~ ~ ~ ~`",
    "nor `x ~ ~`",
    "",
    "s",
    "nor `x ~ ~`",
    "nor `x*7 ~ x*2 [x x]`",
    "nor `x ~ ~`",
    "nor `x*7 ~ x*2 [x x]`",
    "nor `~ x ~ x ~ [x x]`",
    "nor `~ x ~ x*3 ~ [x x] `",
    "nor `~ x ~ x*3 ~ [x x] ~`",
    "nor `x*5 ~ [x x]`"
   ],
   "gate": true,
   "solo": false,
   "mute": false,
   "loop": true,
   "executed": false,
   "selected": false,
   "cid": 23,
   "activeSceneIndex": 2
  },
  {
   "scene": "8_9_10m18",
   "name": "d4",
   "type": "Tidal",
   "steps": 14,
   "rate": 2,
   "time": 0,
   "transition": "(clutchIn 4)",
   "cells": [
    "",
    "s",
    "fil",
    "",
    "",
    "",
    "",
    "",
    "",
    "s",
    "fil",
    "",
    "",
    ""
   ],
   "gate": true,
   "solo": false,
   "mute": false,
   "loop": true,
   "executed": false,
   "selected": false,
   "cid": 24,
   "activeSceneIndex": 3
  },
  {
   "scene": "lea",
   "name": "d1",
   "type": "Tidal",
   "steps": 17,
   "rate": 8,
   "time": 0,
   "transition": "(clutchIn 4)",
   "cells": [
    "",
    "",
    "kc2 `trunc 0.3 $ off 0.5(#n \"{3*2}%4\")` `4`",
    "",
    "kc `off 0.5(#n \"{3*2}%4\")`",
    "",
    "kc `every 5 (cap 0.2 0.3)$ every 1 (#end 0.2) $ off 0.5(#n \"{3*2}%4\")`",
    "kc2 `every 5 (cap 0.2 0.3)$ every 1 (#end 0.2) $ off 0.5(#n \"{3*2}%4\")` `4`",
    "kc `off 0.5(#n \"{3*2}%4\")`",
    "",
    "kc `every 5 (cap 0.2 0.3)$ every 1 (#end 0.2) $ off 0.5(#n \"{3*2}%4\")`",
    "kc2 `every 5 (cap 0.2 0.3)$ every 1 (#end 0.2) $ off 0.5(#n \"{3*2}%4\")` `4`",
    "",
    "kc `every 5 (cap 0.2 0.3)$ every 12 (#end 0.2) $ off 0.5(#n \"{3*2 3 <3*3? 2>}%4\")`",
    "kc `every 5 (cap 0.2 0.3)$ every 12 (#end 0.2) $ off 0.5(#n \"{2 3*2 3 <[3 2] 2*2?>}%4\")`",
    "kc `every 12 (#end 0.2) $ off 0.5(#n \"{2 3*2 3 <[3 2] 2*2?>}%4\")`",
    "kc `off 0.5(#n \"{3*2}%4\")`"
   ],
   "gate": true,
   "solo": false,
   "mute": false,
   "loop": true,
   "executed": false,
   "selected": false,
   "cid": 42
  },
  {
   "scene": "lea",
   "name": "d2",
   "type": "Tidal",
   "steps": 16,
   "rate": 8,
   "time": 0,
   "transition": "(clutchIn 4)",
   "cells": [
    "",
    "",
    "",
    "",
    "sn `~ 1 ~` `gen1`",
    "sn `~ 1 ~ <[ ~ 1] [1 ~] > <<~ 1 ~>  1*2>` `gen1`",
    "sn `~ 1 ~ <[ ~ 1] [1 ~] > <<~ 1 ~>  1*2>` `gen8`",
    "s",
    "sn `~ 1 ~ <[ ~ 1] [1 ~] > <<~ 1 ~>  1*2>` `gen3`",
    "sn `~ 1 ~ 1` `gen3`",
    "",
    "sn `~ 1 ~  <<1 1 ~>  1*2>` `gen4`",
    "",
    "",
    "",
    ""
   ],
   "gate": true,
   "solo": false,
   "mute": false,
   "loop": true,
   "executed": false,
   "selected": false,
   "cid": 43
  },
  {
   "scene": "lea",
   "name": "d3",
   "type": "Tidal",
   "steps": 16,
   "rate": 8,
   "time": 0,
   "transition": "(clutchIn 4)",
   "cells": [
    "",
    "",
    "",
    "",
    "",
    "",
    "hh `~ 3 ~ <[ 3 3] [3 ~] > <<5 3 4>  3*2>` `gen5`",
    "hh `4 3 [[ 3 3] [3 ~]] <<5 3 4>  3*2>` `gen5`",
    "s",
    "hh `4 3 [[ 3 3] [3 ~]] <<[4 3] <3 4*2>>  3*2>,3` `gen5`",
    "hh `[4 3] 3*2 [[ 3 3] [3 ~]] <<[4 3] <3 4*2>>  3*2>,3` `gen5`",
    "",
    "hh `~ ~4 3 [[ 3 3] [3 ~]] <<5 3 4>  3*2>` `gen5`",
    "",
    "",
    ""
   ],
   "gate": true,
   "solo": false,
   "mute": false,
   "loop": true,
   "executed": false,
   "selected": false,
   "cid": 44
  },
  {
   "scene": "lea",
   "name": "d4",
   "type": "Tidal",
   "steps": 16,
   "rate": 8,
   "time": 0,
   "transition": "(anticipateIn 8)",
   "cells": [
    "",
    "nord `4` `~ [x x] [x x x]` `sine` ",
    "",
    "nord `\"<3 4>\"` `~ [x x] [x x x]` `sine` ",
    "nord `\"<3 2>\"` `~ [x x] [x x x] x*2` `sine` ",
    "nord `\"<3 2>\"` `~ [x x] [x x x] x*2` `sine` ",
    "nord `\"<4>\"` `[x x] [x x] [x x x] x*2` `sine` ",
    "nord `\"<4>\"` `[x x] [x x] [x x x] <x*2 x*3>` `sine` ",
    "",
    "",
    "nord `4` `~ [x x] [x x x]` `sine` ",
    "",
    "nord `\"<3 4>\"` `~ [x x] [x x x]` `sine` ",
    "",
    "",
    "nord `\"6\"` `~ [x x] [x x x]` `sine` "
   ],
   "gate": true,
   "solo": false,
   "mute": false,
   "loop": true,
   "executed": false,
   "selected": false,
   "cid": 45
  },
  {
   "scene": "8_9_10m18",
   "name": "d5",
   "type": "Tidal",
   "steps": 14,
   "rate": 2,
   "time": 0,
   "transition": "",
   "cells": [
    "",
    "s",
    "",
    "",
    "",
    "",
    "acd",
    "",
    "",
    "s",
    "",
    "",
    "",
    ""
   ],
   "gate": true,
   "solo": false,
   "mute": false,
   "loop": true,
   "executed": false,
   "selected": false,
   "cid": 46,
   "activeSceneIndex": 4
  },
  {
   "scene": "machine",
   "name": "d1",
   "type": "Tidal",
   "steps": 21,
   "rate": 14,
   "time": 0,
   "transition": "(anticipateIn 4)",
   "cells": [
    "",
    "",
    "",
    "pat `trunc 0.5` `9`",
    "pat `trunc 1` `9`",
    "pat `every 5 (#speed \"-1\") $ trunc 0.7` `3`",
    "pat `every 2 (#speed \"-1\") $ trunc 1` `9`",
    "pat `off 0.5 (#speed 0.5)$ trunc 0.5` `9`",
    "pat `trunc 1` `9`",
    "pat `every 3 (#speed \"-1\") $ chop 7 $ trunc 0.7` `3`",
    "pat `trunc 0.2` `9`",
    "pat `chop 14 $ every 5 (#cut 1) $sometimesBy 0.7 (trunc 0.71)` `7`",
    "pat `chop 7 $ every 5 (#cut 1) $sometimesBy 0.2 (cap 0.2 0.3)` `7`",
    "pat `off 0.5 (#speed 0.5)$ trunc 0.5` `9`",
    "pat `off 0.5 (|*|up \"<2 4>\")$ trunc 0.5` `9`",
    "pat `off 0.5 (|*|up \"<1.2 1.4>\")$ trunc 0.5` `9`",
    "pat `off 0.5 (#speed 0.5)$ trunc 0.7` `9`",
    "pat `off 0.5 (|*|up \"<2 4>\")$ trunc 1` `9`",
    "pat `off 0.5 (|*|up \"<1.2 1.4>\")$ trunc 0.5` `9`",
    "pat `off 0.5 (#speed 0.5)$ trunc 0.7` `9`",
    "pat `off 0.5 (|*|up \"<2 4>\")$ trunc 1` `9`"
   ],
   "gate": true,
   "solo": false,
   "mute": false,
   "loop": true,
   "executed": false,
   "selected": false,
   "cid": 48,
   "activeSceneIndex": 0
  },
  {
   "scene": "machine",
   "name": "d2",
   "type": "Tidal",
   "steps": 21,
   "rate": 14,
   "time": 0,
   "transition": "(clutchIn 4)",
   "cells": [
    "",
    "",
    "",
    "apt `2`",
    "apt `~`",
    "apt `4`",
    "apt `3`",
    "apt `4`",
    "s",
    "apt `5`",
    "apt `~`",
    "apt `0`",
    "apt `3`",
    "apt `1`",
    "",
    "apt `3`",
    "apt `1`",
    "",
    "",
    "apt `1`",
    "apt2 `rarely(cap 0.2 0.3)` `3`"
   ],
   "gate": true,
   "solo": false,
   "mute": false,
   "loop": true,
   "executed": false,
   "selected": false,
   "cid": 49,
   "activeSceneIndex": 1
  },
  {
   "scene": "machine",
   "name": "d3",
   "type": "Tidal",
   "steps": 21,
   "rate": 14,
   "time": 0,
   "transition": "",
   "cells": [
    "",
    "",
    "",
    "amb ",
    "amb",
    "",
    "amb",
    "s",
    "amb",
    "",
    "",
    "",
    "h2 `9`",
    "",
    "",
    "s",
    "",
    "",
    "s",
    "",
    ""
   ],
   "gate": true,
   "solo": false,
   "mute": false,
   "loop": true,
   "executed": false,
   "selected": false,
   "cid": 50,
   "activeSceneIndex": 2
  },
  {
   "scene": "machine",
   "name": "d4",
   "type": "Tidal",
   "steps": 21,
   "rate": 14,
   "time": 0,
   "transition": "(clutchIn 2)",
   "cells": [
    "",
    "",
    "nord",
    "",
    "nord",
    "",
    "nord",
    "s",
    "",
    "nord",
    "",
    "",
    "s",
    "nord",
    "",
    "s",
    "nord",
    "",
    "s",
    "nord",
    ""
   ],
   "gate": true,
   "solo": false,
   "mute": false,
   "loop": true,
   "executed": false,
   "selected": false,
   "cid": 51,
   "activeSceneIndex": 3
  },
  {
   "scene": "machine",
   "name": "d5",
   "type": "Tidal",
   "steps": 21,
   "rate": 14,
   "time": 0,
   "transition": "(anticipateIn 4)",
   "cells": [
    "",
    "",
    "md",
    "",
    "",
    "",
    "",
    "",
    "",
    "",
    "md",
    "",
    "s",
    "md",
    "",
    "s",
    "md",
    "",
    "s",
    "md",
    ""
   ],
   "gate": true,
   "solo": false,
   "mute": false,
   "loop": true,
   "executed": false,
   "selected": false,
   "cid": 52,
   "activeSceneIndex": 4
  },
  {
   "scene": "machine",
   "name": "d6",
   "type": "Tidal",
   "steps": 21,
   "rate": 32,
   "time": 0,
   "transition": "(anticipateIn 2)",
   "cells": [
    "",
    "md2 `trunc 0.25`",
    "",
    "md2 `trunc 0.3`",
    "md2 `trunc 0.75`",
    "md2 `trunc 1`",
    "s",
    "",
    "md2 `inside 2(cap 0.2 0.3) `",
    "md2 `slow 5 $ off 0.5 (trunc 0.2) $ every 3(rev)`",
    "md2 `spaceOut[0.2..2]`",
    "md2 `slow 6 $ off 0.5 (trunc 0.2) $ every 3(rev)`",
    "s",
    "md2 `off 0.5 (trunc 0.2) $ every 3(rev)`",
    "s",
    "md2 `every 3(rev)`",
    "md2 `inside 2(cap 0.2 0.3) `",
    "s",
    "s",
    "md2 `off 0.5 (trunc 0.2) $ every 3(rev)`",
    "s"
   ],
   "gate": true,
   "solo": false,
   "mute": false,
   "loop": true,
   "executed": false,
   "selected": false,
   "cid": 53
  },
  {
   "scene": "lea",
   "name": "d5",
   "type": "Tidal",
   "steps": 15,
   "rate": 8,
   "time": 0,
   "transition": "",
   "cells": [
    "",
    "",
    "kc2 `trunc 0.3 $ off 0.5(#n \"{3*2}%4\")` `4`",
    "s",
    "",
    "",
    "",
    "",
    "h2 `1`",
    "h2 `8` ",
    "h2 `4`",
    "h2 `7`",
    "h2 `5`",
    "h2 `6`",
    ""
   ],
   "gate": true,
   "solo": false,
   "mute": false,
   "loop": true,
   "executed": false,
   "selected": false,
   "cid": 54
  },
  {
   "scene": "lea2",
   "name": "d1",
   "type": "Tidal",
   "steps": 17,
   "rate": 8,
   "time": 14,
   "transition": "(clutchIn 4)",
   "cells": [
    "",
    "",
    "kc2 `trunc 0.3 $ off 0.5(#n \"{3*2}%4\")` `1`",
    "kc2 `off 0.5(#n \"{3*2}%5\")` `3`",
    "kc2 `off 0.5(#n \"{3*2}%5\")` `2`",
    "",
    "kc2 `off 0.5(#n \"{~  ~ <2*2 [ 2 2 2]> ,3*2}%5\")` `2`",
    "kc2 `off 0.5(#n \"{~  ~ <2*2 [ 2 2 2]> ,3*2}%5\")` `3`",
    "kc `off 0.5(#n \"{3*2}%4\")`",
    "",
    "",
    "",
    "s",
    "kc `every 5 (cap 0.2 0.3)$ every 12 (#end 0.2) $ off 0.5(#n \"{3*2 3 <3*3? 2>}%5\")` ",
    "kc `every 5 (cap 0.2 0.3)$ every 12 (#end 0.2) $ off 0.5(#n \"{2 3*2 3 <[3 2] 2*2?>}%4\")`",
    "kc `every 12 (#end 0.2) $ off 0.5(#n \"{2 3*2 3 <[3 2] 2*2?>}%4\")`",
    "kc `off 0.5(#n \"{3*2}%4\")`"
   ],
   "gate": true,
   "solo": false,
   "mute": false,
   "loop": true,
   "executed": false,
   "selected": false,
   "cid": 42,
   "activeSceneIndex": 0
  },
  {
   "scene": "lea2",
   "name": "d2",
   "type": "Tidal",
   "steps": 17,
   "rate": 8,
   "time": 14,
   "transition": "(clutchIn 4)",
   "cells": [
    "",
    "",
    "sn `~ 1 ~` `gen1`",
    "",
    "sn `~ 1 ~` `gen1`",
    "sn `~ 1 ~ <[ ~ 1] [1 ~] > <<~ 1 ~>  1*2>` `gen1`",
    "sn `~ 1 ~ <[ ~ 1] [1 ~] > <<~ 1 ~>  1*2>` `gen8`",
    "s",
    "sn `~ 1 ~ <[ ~ 1] [1 ~] > <<~ 1 ~>  1*2>` `gen3`",
    "s",
    "sn `~ 1 ~ <[ ~ 1] [1 ~] > <<1 1 ~>  1*2>` `gen3`",
    "sn `~ 1 ~  <<1 1 ~>  1*2>` `gen4`",
    "",
    "",
    "s",
    "",
    ""
   ],
   "gate": true,
   "solo": false,
   "mute": false,
   "loop": true,
   "executed": false,
   "selected": false,
   "cid": 43,
   "activeSceneIndex": 1
  },
  {
   "scene": "lea2",
   "name": "d3",
   "type": "Tidal",
   "steps": 17,
   "rate": 8,
   "time": 14,
   "transition": "(clutchIn 4)",
   "cells": [
    "",
    "",
    "",
    "",
    "",
    "",
    "hh `~ 3 ~ <[ 3 3] [3 ~] > <<5 3 4>  3*2>` `gen5`",
    "hh `4 3 [[ 3 3] [3 ~]] <<5 3 4> 3*2>` `gen5`",
    "s",
    "",
    "hh `[4 3] 3*2 [[ 3 3] [3 ~]] <<[4 3] <3 4*2>>  3*2>,3` `gen5`",
    "",
    "hh `~ ~4 3 [[ 3 3] [3 ~]] <<5 3 4>  3*2>` `gen5`",
    "",
    "s",
    "hh `4 3 [[ 3 3] [3 ~]] <<[4 3] <3 4*2>>  3*2>,3` `gen5`",
    ""
   ],
   "gate": true,
   "solo": false,
   "mute": false,
   "loop": true,
   "executed": false,
   "selected": false,
   "cid": 44,
   "activeSceneIndex": 2
  },
  {
   "scene": "lea2",
   "name": "d4",
   "type": "Tidal",
   "steps": 17,
   "rate": 8,
   "time": 14,
   "transition": "(anticipateIn 8)",
   "cells": [
    "",
    "nord `4` `~ [x x] [x x x]` `sine` ",
    "",
    "nord `\"<3 4>\"` `~ [x x] [x x x]` `sine` ",
    "s",
    "nord `\"<3 2>\"` `~ [x x] [x x x] x*2` `sine` ",
    "nord `\"<4>\"` `[x x] [x x] [x x x] x*2` `sine` ",
    "nord `\"<4>\"` `[x x] [x x] [x x x] <x*2 x*3>` `sine` ",
    "",
    "",
    "nord `4` `~ [x x] [x x x]` `sine` ",
    "",
    "nord `\"<3 4>\"` `~ [x x] [x x x]` `sine` ",
    "",
    "s",
    "nord `\"6\"` `~ [x x] [x x x]` `sine` ",
    ""
   ],
   "gate": true,
   "solo": false,
   "mute": false,
   "loop": true,
   "executed": false,
   "selected": false,
   "cid": 45,
   "activeSceneIndex": 3
  },
  {
   "scene": "lea2",
   "name": "d5",
   "type": "Tidal",
   "steps": 17,
   "rate": 4,
   "time": 27,
   "transition": "(anticipateIn 8)",
   "cells": [
    "",
    "",
    "",
    "",
    "",
    "h22 `8`",
    "h22 `4`",
    "s",
    "h2 `1`",
    "s",
    "h2 `4`",
    "h2 `7`",
    "h2 `5`",
    "h2 `6`",
    "s",
    "h2 `7`",
    ""
   ],
   "gate": true,
   "solo": false,
   "mute": false,
   "loop": true,
   "executed": false,
   "selected": false,
   "cid": 54,
   "activeSceneIndex": 4
  },
  {
   "scene": "lea2",
   "name": "d6",
   "type": "Tidal",
   "steps": 17,
   "rate": 8,
   "time": 14,
   "transition": "(clutchIn 4)",
   "cells": [
    "",
    "",
    "",
    "",
    "",
    "",
    "",
    "",
    "",
    "",
    "s",
    "",
    "nba  `~ [x x] [x x x] x*2` `rand` `4`",
    "nba  `~ [x x] [x x x] x*2` `sine` `4:5`",
    "s",
    "nba  `~ [x x] [x x x] x*2` `sine` `4:1`",
    ""
   ],
   "gate": true,
   "solo": false,
   "mute": false,
   "loop": true,
   "executed": false,
   "selected": false,
   "cid": 66,
   "activeSceneIndex": 5
  },
  {
   "scene": "lea2",
   "name": "d7",
   "type": "Tidal",
   "steps": 17,
   "rate": 8,
   "time": 14,
   "transition": "(clutchIn 4)",
   "cells": [
    "",
    "",
    "kc2 `trunc 0.3 $ off 0.5(#n \"{3*2}%4\")` `4`",
    "",
    "",
    "",
    "",
    "",
    "kc `off 0.5(#n \"{3*2}%4\")`",
    "amb",
    "kc2 `every 5 (cap 0.2 0.3)$ every 1 (#end 0.2) $ off 0.5(#n \"{3*2}%4\")` `4`",
    "s",
    "",
    "",
    "amb",
    "",
    ""
   ],
   "gate": true,
   "solo": false,
   "mute": false,
   "loop": true,
   "executed": false,
   "selected": false,
   "cid": 67,
   "activeSceneIndex": 6
  },
  {
   "scene": "lmd",
   "name": "d1",
   "type": "Tidal",
   "steps": 17,
   "rate": 8,
   "time": 24,
   "transition": "(clutchIn 4)",
   "cells": [
    "",
    "",
    "",
    "",
    "",
    "",
    "    ",
    "",
    "kc2 `off 0.5(#begin 0.2)` `2`",
    "kc2 `off 0.5(#begin 0.2)` `6`",
    "kc2 `every 5 (cap 0.2 0.3)$ every 1 (#end 0.2) $ off 0.5(#n \"{3*2}%4\")` `7`",
    "",
    "kc2 `trunc 0.9` `2`",
    "kc2 `trunc 0.2` `1`",
    "kc `every 5 (cap 0.2 0.3)$ every 12 (#end 0.2) $ off 0.5(#n \"{2 3*2 3 <[3 2] 2*2?>}%4\")`",
    "kc `every 12 (#end 0.2) $ off 0.5(#n \"{2 3*2 3 <[3 2] 2*2?>}%4\")`",
    "kc `off 0.5(#n \"{3*2}%4\")`"
   ],
   "gate": true,
   "solo": false,
   "mute": false,
   "loop": true,
   "executed": false,
   "selected": false,
   "cid": 42,
   "activeSceneIndex": 0
  },
  {
   "scene": "lmd",
   "name": "d2",
   "type": "Tidal",
   "steps": 17,
   "rate": 8,
   "time": 24,
   "transition": "",
   "cells": [
    "",
    "nord `4` `scaleP`",
    "nord `8` `harmonise`",
    "nord `4` `harmonise`",
    "",
    "",
    "",
    "",
    "",
    "kc2 `foldp $ off ]0.5((#speed \"<1.2 1.5 1 1.2>\").(#begin 0.2).(#n \"{3 [4 <3 ~>] 3}%5\"))` `8`",
    "sq",
    "kc2 `foldp $ off 0.5((#speed \"<1.2 1.5 1 1.2>\").(#begin 0.2).(#n \"{3 [4 <3 ~>] 3}%5\"))` `9`",
    "",
    "kc2 `off 0.5(#s  \"water\")` `1`",
    "kc2 `off 0.5(#s \"gen2\")` `1`",
    "",
    ""
   ],
   "gate": true,
   "solo": false,
   "mute": false,
   "loop": true,
   "executed": false,
   "selected": false,
   "cid": 45,
   "activeSceneIndex": 1
  },
  {
   "scene": "lmd",
   "name": "d3",
   "type": "Tidal",
   "steps": 17,
   "rate": 4,
   "time": 38,
   "transition": "(clutchIn 4)",
   "cells": [
    "",
    "",
    "",
    "h22 `4`",
    "h22 `2`",
    "",
    "s",
    "",
    "h2 `7`",
    "",
    "s",
    "sq",
    "",
    "",
    "",
    "",
    ""
   ],
   "gate": true,
   "solo": false,
   "mute": false,
   "loop": true,
   "executed": false,
   "selected": false,
   "cid": 54,
   "activeSceneIndex": 2
  },
  {
   "scene": "lmd",
   "name": "d4",
   "type": "Tidal",
   "steps": 17,
   "rate": 8,
   "time": 24,
   "transition": "(clutchIn 4)",
   "cells": [
    "",
    "s",
    "",
    "",
    "s",
    "s",
    "nba",
    "",
    "",
    "amb",
    "",
    "",
    "",
    "",
    "",
    "",
    ""
   ],
   "gate": true,
   "solo": false,
   "mute": false,
   "loop": true,
   "executed": false,
   "selected": false,
   "cid": 67,
   "activeSceneIndex": 3
  },
  {
   "scene": "lmd",
   "name": "d5",
   "type": "Tidal",
   "steps": 12,
   "rate": 8,
   "time": 24,
   "transition": "",
   "cells": [
    "",
    "",
    "h2 `4`",
    "",
    "h2 `5`",
    "h2 `6`",
    "s",
    "h2 `7`",
    "h2 `1`",
    "",
    "",
    ""
   ],
   "gate": true,
   "solo": false,
   "mute": false,
   "loop": true,
   "executed": false,
   "selected": false,
   "cid": 62,
   "activeSceneIndex": 4
  },
  {
   "scene": "lmd",
   "name": "d6",
   "type": "Tidal",
   "steps": 10,
   "rate": 8,
   "time": 23,
   "transition": "",
   "cells": [
    "",
    "",
    "sq2 `trunc 0.3` `1`",
    "sq2 `trunc 0.5` `2`",
    "sq2 `trunc 0.5` `2`",
    "",
    "",
    "",
    "",
    ""
   ],
   "gate": true,
   "solo": false,
   "mute": false,
   "loop": true,
   "executed": false,
   "selected": false,
   "cid": 63,
   "activeSceneIndex": 5
  },
  {
   "scene": "lmd",
   "name": "d7",
   "type": "Tidal",
   "steps": 8,
   "rate": 8,
   "time": 7,
   "transition": "",
   "cells": [
    "",
    "",
    "",
    "",
    "",
    "sq",
    "s",
    ""
   ],
   "gate": false,
   "solo": false,
   "mute": false,
   "loop": true,
   "executed": false,
   "selected": false,
   "cid": 64
  },
  {
   "scene": "poolx",
   "name": "d1",
   "type": "Tidal",
   "steps": 14,
   "rate": 2,
   "time": 10,
   "transition": "(clutchIn 2)",
   "cells": [
    "",
    "foil `release 2`",
    "foil `release 4`",
    "foil `delay 0.3`",
    "foil `shape 0.3`",
    "foil `vowel \"<p e>\"`",
    "foil `lpf 8000 #lpq 0.3`",
    "",
    "foil `lpf (slow 4 $ scale 3000 9000 $ sine1) #lpq 0.5`",
    "",
    "",
    "",
    "",
    ""
   ],
   "gate": true,
   "solo": false,
   "mute": false,
   "loop": true,
   "executed": false,
   "selected": false,
   "cid": 52,
   "activeSceneIndex": 0
  },
  {
   "scene": "poolx",
   "name": "d2",
   "type": "Tidal",
   "steps": 14,
   "rate": 2,
   "time": 10,
   "transition": "(clutchIn 2)",
   "cells": [
    "",
    "",
    "foil2",
    "",
    "",
    "s",
    "",
    "",
    "",
    "",
    "",
    "",
    "",
    ""
   ],
   "gate": true,
   "solo": false,
   "mute": false,
   "loop": true,
   "executed": false,
   "selected": false,
   "cid": 53,
   "activeSceneIndex": 1
  },
  {
   "scene": "poolx",
   "name": "d3",
   "type": "Tidal",
   "steps": 14,
   "rate": 2,
   "time": 9,
   "transition": "(clutchIn 2)",
   "cells": [
    "",
    "",
    "",
    "pat",
    "",
    "",
    "",
    "",
    "",
    "",
    "",
    "",
    "",
    ""
   ],
   "gate": true,
   "solo": false,
   "mute": false,
   "loop": true,
   "executed": false,
   "selected": false,
   "cid": 54,
   "activeSceneIndex": 2
  },
  {
   "scene": "poolx",
   "name": "d4",
   "type": "Tidal",
   "steps": 14,
   "rate": 2,
   "time": 8,
   "transition": "(clutchIn 2)",
   "cells": [
    "",
    "",
    "patslow",
    "",
    "",
    "",
    "",
    "",
    "",
    "",
    "",
    "",
    "",
    ""
   ],
   "gate": true,
   "solo": false,
   "mute": false,
   "loop": true,
   "executed": false,
   "selected": false,
   "cid": 55,
   "activeSceneIndex": 3
  },
  {
   "scene": "poolx",
   "name": "d5",
   "type": "Tidal",
   "steps": 14,
   "rate": 2,
   "time": 7,
   "transition": "(clutchIn 2)",
   "cells": [
    "",
    "",
    "kobass",
    "",
    "pat",
    "s",
    "",
    "",
    "",
    "",
    "",
    "",
    "",
    ""
   ],
   "gate": true,
   "solo": false,
   "mute": false,
   "loop": true,
   "executed": false,
   "selected": false,
   "cid": 56,
   "activeSceneIndex": 4
  },
  {
   "scene": "poolx",
   "name": "d6",
   "type": "Tidal",
   "steps": 8,
   "rate": 2,
   "time": 7,
   "transition": "(clutchIn 2)",
   "cells": [
    "",
    "s",
    "",
    "kob2",
    "",
    "",
    "",
    ""
   ],
   "gate": true,
   "solo": false,
   "mute": false,
   "loop": true,
   "executed": false,
   "selected": false,
   "cid": 58,
   "activeSceneIndex": 5
  },
  {
   "scene": "poolx",
   "name": "d7",
   "type": "Tidal",
   "steps": 9,
   "rate": 2,
   "time": 6,
   "transition": "(clutchIn 2)",
   "cells": [
    "",
    "s",
    "",
    "",
    "md3",
    "",
    "",
    "md2",
    ""
   ],
   "gate": true,
   "solo": false,
   "mute": false,
   "loop": true,
   "executed": false,
   "selected": false,
   "cid": 59,
   "activeSceneIndex": 6
  },
  {
   "scene": "poolx",
   "name": "d8",
   "type": "Tidal",
   "steps": 8,
   "rate": 2,
   "time": 6,
   "transition": "(clutchIn 2)",
   "cells": [
    "",
    "s",
    "",
    "",
    "mdh",
    "",
    "",
    ""
   ],
   "gate": true,
   "solo": false,
   "mute": false,
   "loop": true,
   "executed": false,
   "selected": false,
   "cid": 60,
   "activeSceneIndex": 7
  },
  {
   "scene": "thorwview",
   "name": "d1",
   "type": "Tidal",
   "steps": 14,
   "rate": 2,
   "time": 12,
   "transition": "(clutchIn 4)",
   "cells": [
    "",
    "s",
    "pto `trunc 0.5`",
    "pto `trunc 0.8`",
    "pto `trunc 1`",
    "pto `juxBy 0.1(#s \"bass1\") $ slow 2`",
    "pto `trunc 1` `2`",
    "",
    "pto `trunc 1` `6`",
    "s",
    "pto `trunc 1` `8`",
    "pto `trunc 0.5 $ slow 1` `3`",
    "pto `juxBy 0.1(#s \"foil2\") $ slow 1` `6`",
    "pto `slow 3 $ cap 0.2 0.3`  `6`"
   ],
   "gate": true,
   "solo": true,
   "mute": false,
   "loop": true,
   "executed": false,
   "selected": false,
   "cid": 21,
   "activeSceneIndex": 0
  },
  {
   "scene": "thorwview",
   "name": "d2",
   "type": "Tidal",
   "steps": 14,
   "rate": 1,
   "time": 23,
   "transition": "(clutchIn 4)",
   "cells": [
    "",
    "s",
    "pat ",
    "",
    "",
    "s",
    "pat `gen3`",
    "",
    "s",
    "pat `gen6`",
    "",
    "",
    "",
    "pat `gen8`"
   ],
   "gate": true,
   "solo": false,
   "mute": false,
   "loop": true,
   "executed": false,
   "selected": false,
   "cid": 22,
   "activeSceneIndex": 1
  },
  {
   "scene": "thorwview",
   "name": "d3",
   "type": "Tidal",
   "steps": 14,
   "rate": 2,
   "time": 12,
   "transition": "(clutchIn 4)",
   "cells": [
    "",
    "s",
    "nor `x ~ ~ ~ ~`",
    "nor `x ~ ~`",
    "",
    "s",
    "nor `x ~ ~`",
    "nor `x*7 ~ x*2 [x x]`",
    "nor `x ~ ~`",
    "nor `x*7 ~ x*2 [x x]`",
    "nor `~ x ~ x ~ [x x]`",
    "nor `~ x ~ x*3 ~ [x x] `",
    "nor `~ x ~ x*3 ~ [x x] ~`",
    "nor `x*5 ~ [x x]`"
   ],
   "gate": true,
   "solo": false,
   "mute": false,
   "loop": true,
   "executed": false,
   "selected": false,
   "cid": 23,
   "activeSceneIndex": 2
  },
  {
   "scene": "thorwview",
   "name": "d4",
   "type": "Tidal",
   "steps": 14,
   "rate": 2,
   "time": 12,
   "transition": "(clutchIn 4)",
   "cells": [
    "",
    "s",
    "fil",
    "hat",
    "",
    "",
    "",
    "",
    "",
    "s",
    "fil",
    "",
    "",
    ""
   ],
   "gate": true,
   "solo": false,
   "mute": false,
   "loop": true,
   "executed": false,
   "selected": false,
   "cid": 24,
   "activeSceneIndex": 3
  },
  {
   "scene": "thorwview",
   "name": "d5",
   "type": "Tidal",
   "steps": 14,
   "rate": 2,
   "time": 12,
   "transition": "",
   "cells": [
    "",
    "s",
    "",
    "",
    "",
    "",
    "acd",
    "",
    "",
    "s",
    "",
    "",
    "",
    ""
   ],
   "gate": true,
   "solo": false,
   "mute": false,
   "loop": true,
   "executed": false,
   "selected": false,
   "cid": 46,
   "activeSceneIndex": 4
  },
  {
   "scene": "blp1",
   "name": "d1",
   "type": "Tidal",
   "steps": 13,
   "rate": 8,
   "time": 24,
   "transition": "(clutchIn 2)",
   "cells": [
    "",
    "",
    "pat `blp_nqst` `comb`",
    "pat1",
    "pat2",
    "",
    "",
    "",
    "",
    "",
    "",
    "",
    ""
   ],
   "gate": false,
   "solo": false,
   "mute": false,
   "loop": true,
   "executed": false,
   "selected": false,
   "cid": 71
  },
  {
   "scene": "blp1",
   "name": "d2",
   "type": "Tidal",
   "steps": 10,
   "rate": 8,
   "time": 0,
   "transition": "(clutchIn 2)",
   "cells": [
    "",
    "",
    "blp",
    "glt",
    "pat `blp_nqst` `comb`",
    "",
    "",
    "",
    "",
    ""
   ],
   "gate": false,
   "solo": false,
   "mute": false,
   "loop": true,
   "executed": false,
   "selected": false,
   "cid": 72
  },
  {
   "scene": "blp1",
   "name": "d3",
   "type": "Tidal",
   "steps": 8,
   "rate": 2,
   "time": 4,
   "transition": "(clutchIn 2)",
   "cells": [
    "",
    "",
    "blp2",
    "s",
    "glt",
    "",
    "",
    ""
   ],
   "gate": true,
   "solo": false,
   "mute": false,
   "loop": true,
   "executed": false,
   "selected": false,
   "cid": 73,
   "activeSceneIndex": 2
  },
  {
   "scene": "blp1",
   "name": "d4",
   "type": "Tidal",
   "steps": 6,
   "rate": 2,
   "time": 3,
   "transition": "(clutchIn 2)",
   "cells": [
    "",
    "s",
    "blp2",
    "",
    "",
    ""
   ],
   "gate": true,
   "solo": false,
   "mute": false,
   "loop": true,
   "executed": false,
   "selected": false,
   "cid": 74,
   "activeSceneIndex": 3
  },
  {
   "scene": "blp1",
   "name": "d5",
   "type": "Tidal",
   "steps": 11,
   "rate": 8,
   "time": 8,
   "transition": "",
   "cells": [
    "",
    "",
    "",
    "",
    "zow `|*|up \"<0>\"`",
    "zow `|*|up \"<2 5>\"`",
    "zow `|+|n \"<24>\"`",
    "zow `|+|up \"<12>\"`",
    "",
    "",
    ""
   ],
   "gate": true,
   "solo": false,
   "mute": false,
   "loop": true,
   "executed": false,
   "selected": false,
   "cid": 69,
   "activeSceneIndex": 4
  },
  {
   "scene": "blp1",
   "name": "d6",
   "type": "Tidal",
   "steps": 8,
   "rate": 8,
   "time": 0,
   "transition": "",
   "cells": [
    "",
    "",
    "",
    "nord",
    "",
    "",
    "",
    ""
   ],
   "gate": false,
   "solo": false,
   "mute": false,
   "loop": true,
   "executed": false,
   "selected": false,
   "cid": 70
  },
  {
   "scene": "blp2",
   "name": "d1",
   "type": "Tidal",
   "steps": 9,
   "rate": 8,
   "time": 11,
   "transition": "",
   "cells": [
    "",
    "pat",
    "",
    "",
    "",
    "",
    "",
    "",
    ""
   ],
   "gate": true,
   "solo": false,
   "mute": false,
   "loop": true,
   "executed": false,
   "selected": false,
   "cid": 71,
   "activeSceneIndex": 0
  },
  {
   "scene": "blp2",
   "name": "d2",
   "type": "Tidal",
   "steps": 9,
   "rate": 8,
   "time": 11,
   "transition": "",
   "cells": [
    "",
    "",
    "",
    "",
    "s",
    "",
    "pat2 `blp_nunu`",
    "",
    ""
   ],
   "gate": true,
   "solo": false,
   "mute": false,
   "loop": true,
   "executed": false,
   "selected": false,
   "cid": 72,
   "activeSceneIndex": 1
  },
  {
   "scene": "blp2",
   "name": "d3",
   "type": "Tidal",
   "steps": 8,
   "rate": 8,
   "time": 0,
   "transition": "",
   "cells": [
    "",
    "",
    "",
    "glt",
    "",
    "",
    "",
    ""
   ],
   "gate": false,
   "solo": false,
   "mute": false,
   "loop": true,
   "executed": false,
   "selected": false,
   "cid": 73
  },
  {
   "scene": "blp2",
   "name": "d4",
   "type": "Tidal",
   "steps": 9,
   "rate": 8,
   "time": 11,
   "transition": "",
   "cells": [
    "",
    "snr `blp3` `#fm 0.9 #fmf 1200`",
    "",
    "snr `blp3*3` `#psratio 0.9 #delayfb 0.8 #delaytime 0.02 #delay 0.66`",
    "snr `blp3*3` `#psratio 0.9 #delayfb 0.8 #delaytime 0.02 #delay 0.66`",
    "snr `blp3` `#fm 0.9 #fmf 2400`",
    "",
    "",
    ""
   ],
   "gate": true,
   "solo": false,
   "mute": false,
   "loop": true,
   "executed": false,
   "selected": false,
   "cid": 74,
   "activeSceneIndex": 3
  },
  {
   "scene": "plock",
   "name": "d1",
   "type": "Tidal",
   "steps": 21,
   "rate": 3,
   "time": 20,
   "transition": "(clutchIn 2)",
   "cells": [
    "",
    "",
    "amen `12` `hallfb`",
    "s",
    "amen `10` `hallfb`",
    "amen `5` `hallfb`",
    "amen `3` `hallfb`",
    "amen `5` `hallfb`",
    "amen `10` `hallfb`",
    "amen `13` `hallfb`",
    "amen2 `4` `hallfb`",
    "amen2 `5` `hallfb`",
    "amen2 `6` `comb`",
    "amen2 `10` `begin`",
    "amen2 `10` `freeze`",
    "amen `3` `hallfb`",
    "amen `5` `hallfb`",
    "amen `1` `hallfb`",
    "amen `2` `comb`",
    "amen `3` `comb`",
    "amen3"
   ],
   "gate": false,
   "solo": false,
   "mute": false,
   "loop": true,
   "executed": false,
   "selected": false,
   "cid": 75,
   "activeSceneIndex": 0
  },
  {
   "scene": "plock",
   "name": "d2",
   "type": "Tidal",
   "steps": 15,
   "rate": 2,
   "time": 0,
   "transition": "",
   "cells": [
    "",
    "",
    "",
    "",
    "",
    "",
    "",
    "",
    "",
    "",
    "",
    "",
    "",
    "",
    "s"
   ],
   "gate": false,
   "solo": false,
   "mute": false,
   "loop": true,
   "executed": false,
   "selected": false,
   "cid": 76,
   "activeSceneIndex": 1
  },
  {
   "scene": "plock",
   "name": "d3",
   "type": "Tidal",
   "steps": 22,
   "rate": 4,
   "time": 61,
   "transition": "",
   "cells": [
    "s",
    "",
    "",
    "",
    "",
    "",
    "",
    "",
    "s",
    "",
    "",
    "",
    "",
    "",
    "",
    "",
    "",
    "",
    "",
    "",
    "",
    ""
   ],
   "gate": true,
   "solo": false,
   "mute": false,
   "loop": true,
   "executed": false,
   "selected": false,
   "cid": 64,
   "activeSceneIndex": 2
  }
 ]
}
